sparta_memcached-0.2.2-py3.11-nspkg.pth
sparta/memcached/__init__.py
sparta/memcached/base.py
sparta/memcached/client.py
sparta/memcached/decorator.py
sparta/memcached/dummy.py
sparta/memcached/thread_mapped_pool_wrapper.py
sparta/memcached/utils.py
sparta/memcached/wrapper.py
sparta_memcached-0.2.2.dist-info/LICENSE
sparta_memcached-0.2.2.dist-info/METADATA
sparta_memcached-0.2.2.dist-info/WHEEL
sparta_memcached-0.2.2.dist-info/namespace_packages.txt
sparta_memcached-0.2.2.dist-info/top_level.txt
sparta_memcached-0.2.2.dist-info/RECORD
